json_pipeline/__init__.py
json_pipeline/transform.py
json_pipeline/utils.py
json_pipeline-0.1.4.dist-info/LICENSE
json_pipeline-0.1.4.dist-info/METADATA
json_pipeline-0.1.4.dist-info/WHEEL
json_pipeline-0.1.4.dist-info/top_level.txt
json_pipeline-0.1.4.dist-info/RECORD
