Metadata-Version: 2.1
Name: json-pipeline
Version: 0.1.4
Summary: Json processing pipeline tools
Home-page: https://github.com/kalessin/json-pipeline
Author: Martin Olveyra
Author-email: molveyra@gmail.com
License: BSD
Platform: UNKNOWN
Classifier: Development Status :: 4 - Beta
Classifier: Intended Audience :: Developers
Classifier: License :: OSI Approved :: BSD License
Classifier: Operating System :: OS Independent
Classifier: Programming Language :: Python :: 3
